odoo/addons/shopinvader_algolia/README.rst
odoo/addons/shopinvader_algolia/__init__.py
odoo/addons/shopinvader_algolia/__manifest__.py
odoo/addons/shopinvader_algolia/hooks.py
odoo/addons/shopinvader_algolia/components/__init__.py
odoo/addons/shopinvader_algolia/components/deleter.py
odoo/addons/shopinvader_algolia/components/exporter.py
odoo/addons/shopinvader_algolia/data/ir_export_product.xml
odoo/addons/shopinvader_algolia/demo/backend_demo.xml
odoo/addons/shopinvader_algolia/demo/product_demo.xml
odoo/addons/shopinvader_algolia/i18n/shopinvader_algolia.pot
odoo/addons/shopinvader_algolia/models/__init__.py
odoo/addons/shopinvader_algolia/models/se_index.py
odoo/addons/shopinvader_algolia/models/shopinvader_category.py
odoo/addons/shopinvader_algolia/models/shopinvader_product.py
odoo/addons/shopinvader_algolia/models/shopinvader_variant.py
odoo/addons/shopinvader_algolia/readme/CONTRIBUTORS.rst
odoo/addons/shopinvader_algolia/readme/CREDITS.rst
odoo/addons/shopinvader_algolia/readme/DESCRIPTION.rst
odoo/addons/shopinvader_algolia/static/description/icon.png
odoo/addons/shopinvader_algolia/static/description/index.html
odoo/addons/shopinvader_algolia/tests/__init__.py
odoo/addons/shopinvader_algolia/tests/test_export.py
odoo/addons/shopinvader_algolia/tests/cassettes/TestAlgoliaBackend.test_10_export_one_product.yaml
odoo/addons/shopinvader_algolia/tests/cassettes/TestAlgoliaBackend.test_20_export_all_products.yaml
odoo/addons/shopinvader_algolia/tests/cassettes/TestAlgoliaBackend.test_30_export_all_categories.yaml
odoo/addons/shopinvader_algolia/views/shopinvader_variant_view.xml
odoo13_addon_shopinvader_algolia-13.0.2.0.0.dist-info/METADATA
odoo13_addon_shopinvader_algolia-13.0.2.0.0.dist-info/WHEEL
odoo13_addon_shopinvader_algolia-13.0.2.0.0.dist-info/top_level.txt
odoo13_addon_shopinvader_algolia-13.0.2.0.0.dist-info/RECORD
